outline_vpn/__init__.py
outline_vpn/outline_vpn.py
outline_vpn_api-6.3.4.dist-info/licenses/LICENSE.txt
outline_vpn_api-6.3.4.dist-info/METADATA
outline_vpn_api-6.3.4.dist-info/WHEEL
outline_vpn_api-6.3.4.dist-info/top_level.txt
outline_vpn_api-6.3.4.dist-info/RECORD
