Metadata-Version: 2.4
Name: outline-vpn-api
Version: 6.3.4
Summary: Python API wrapper for Outline VPN
Author-email: "Jorge Alberto Díaz Orozco (Akiel)" <diazorozcoj@gmail.com>
Maintainer-email: "Jorge Alberto Díaz Orozco (Akiel)" <diazorozcoj@gmail.com>
License-Expression: MIT
Project-URL: Homepage, https://github.com/jadolg/outline-vpn-api
Project-URL: Issues, https://github.com/jadolg/outline-vpn-api/issues
Keywords: outline,vpn,api,wrapper,rest
Requires-Python: >=3.9
License-File: LICENSE.txt
Requires-Dist: requests==2.32.5
Requires-Dist: packaging==25.0
Dynamic: license-file
